mixencoder/__init__.py
mixencoder/models/__init__.py
mixencoder/models/mixencoder.py
mixencoder/models/predictor.py
mixencoder/train/__init__.py
mixencoder/train/trainer.py
mixencoder/utils/__init__.py
mixencoder/utils/finetuner.py
mixencoder/utils/utils.py
mixencoder-0.1.1.dist-info/METADATA
mixencoder-0.1.1.dist-info/WHEEL
mixencoder-0.1.1.dist-info/top_level.txt
mixencoder-0.1.1.dist-info/RECORD
