Metadata-Version: 2.1
Name: mixencoder
Version: 0.1.1
Summary: Package for pre-training embeddings using Mix Encoder.
Home-page: https://github.com/msvenssons/mixencoder
Author: Max Svensson
Author-email: maxiemum789@gmail.com
Classifier: Programming Language :: Python :: 3
Classifier: License :: OSI Approved :: MIT License
Classifier: Operating System :: OS Independent
Requires-Python: >=3.6
Requires-Dist: torch
Requires-Dist: numpy
Requires-Dist: pandas
Requires-Dist: scikit-learn
Requires-Dist: matplotlib
Requires-Dist: tqdm
